clip_protocol/__init__.py
clip_protocol/cli.py
clip_protocol/count_mean/__init__.py
clip_protocol/count_mean/cms_client_mean.py
clip_protocol/count_mean/private_cms_client.py
clip_protocol/count_mean/private_cms_server.py
clip_protocol/hadamard_count_mean/__init__.py
clip_protocol/hadamard_count_mean/private_hcms_client.py
clip_protocol/hadamard_count_mean/private_hcms_server.py
clip_protocol/main/__init__.py
clip_protocol/main/agregate.py
clip_protocol/main/estimate.py
clip_protocol/main/mask.py
clip_protocol/main/setup.py
clip_protocol/utils/__init__.py
clip_protocol/utils/errors.py
clip_protocol/utils/utils.py
clip_protocol-2.2.13.dist-info/METADATA
clip_protocol-2.2.13.dist-info/WHEEL
clip_protocol-2.2.13.dist-info/entry_points.txt
clip_protocol-2.2.13.dist-info/licenses/LICENSE
clip_protocol-2.2.13.dist-info/RECORD
